{
  "sections": {
    "hero_gaming": {
      "type": "hero-gaming",
      "settings": {
        "eyebrow": "STRETCHSENSE",
        "headline": "GAMING",
        "subheadline": "<p>Feel Every Move.</p><p>Own Every Game.</p>",
        "description": "Built for ultimate VR gaming gloves for immersion, precision, and performance.",
        "price": "$495",
        "primary_label": "Buy Now",
        "primary_link": "#",
        "secondary_label": "Learn More",
        "secondary_link": "#"
      }
    },
    "features_bar": {
      "type": "features-bar",
      "blocks": {
        "f1": {
          "type": "feature",
          "settings": {
            "icon": "precision",
            "title": "Precision",
            "description": "360° tracking for total hand awareness."
          }
        },
        "f2": {
          "type": "feature",
          "settings": {
            "icon": "immersion",
            "title": "Immersion",
            "description": "Feel every action in vibrant detail."
          }
        },
        "f3": {
          "type": "feature",
          "settings": {
            "icon": "compatibility",
            "title": "Compatibility",
            "description": "Works with leading VR headsets and games."
          }
        },
        "f4": {
          "type": "feature",
          "settings": {
            "icon": "gamers",
            "title": "Built for Gamers",
            "description": "Lightweight, breathable, and durable."
          }
        }
      },
      "block_order": ["f1", "f2", "f3", "f4"]
    },
    "gameplay_grid": {
      "type": "gameplay-demo-grid",
      "settings": {
        "heading": "Built for Immersion. Designed for Gamers."
      },
      "blocks": {
        "v1": { "type": "video", "settings": { "label": "Gameplay Demo" } },
        "v2": { "type": "video", "settings": { "label": "Gameplay Demo" } },
        "v3": { "type": "video", "settings": { "label": "Gameplay Demo" } },
        "v4": { "type": "video", "settings": { "label": "Gameplay Demo" } }
      },
      "block_order": ["v1", "v2", "v3", "v4"]
    },
    "product_showcase": {
      "type": "product-showcase",
      "settings": {
        "title": "StretchSense Gaming Gloves",
        "price": "$495",
        "cta_label": "Add to Cart",
        "note": "Free shipping worldwide"
      },
      "blocks": {
        "s1": { "type": "spec", "settings": { "text": "Advanced motion tracking" } },
        "s2": { "type": "spec", "settings": { "text": "Haptic feedback" } },
        "s3": { "type": "spec", "settings": { "text": "Bluetooth 5.0 + Wi-Fi" } },
        "s4": { "type": "spec", "settings": { "text": "Up to 12+ hours battery life" } }
      },
      "block_order": ["s1", "s2", "s3", "s4"]
    },
    "guarantee_bar": {
      "type": "guarantee-bar",
      "blocks": {
        "g1": {
          "type": "guarantee",
          "settings": { "icon": "returns", "title": "30-Day Returns", "subtitle": "No-hassle returns" }
        },
        "g2": {
          "type": "guarantee",
          "settings": { "icon": "warranty", "title": "1-Year Warranty", "subtitle": "We've got you covered" }
        },
        "g3": {
          "type": "guarantee",
          "settings": { "icon": "checkout", "title": "Secure Checkout", "subtitle": "Shop with confidence" }
        },
        "g4": {
          "type": "guarantee",
          "settings": { "icon": "shipping", "title": "Global Shipping", "subtitle": "Fast to 30+ countries" }
        }
      },
      "block_order": ["g1", "g2", "g3", "g4"]
    }
  },
  "order": [
    "hero_gaming",
    "features_bar",
    "gameplay_grid",
    "product_showcase",
    "guarantee_bar"
  ]
}
